pyheadtracker/__init__.py
pyheadtracker/diy.py
pyheadtracker/dtypes.py
pyheadtracker/hmd.py
pyheadtracker/supperware.py
pyheadtracker/utils.py
pyheadtracker-0.0.4.dist-info/licenses/LICENSE
pyheadtracker-0.0.4.dist-info/WHEEL
pyheadtracker-0.0.4.dist-info/METADATA
pyheadtracker-0.0.4.dist-info/RECORD
