Metadata-Version: 2.4
Name: pyheadtracker
Version: 0.0.4
Summary: Python package for easy interaction with head tracker hardware.
Author: Felix Holzmüller
Author-email: Felix Holzmüller <holzmueller@iem.at>
License-Expression: MIT
License-File: LICENSE
Classifier: Programming Language :: Python :: 3
Classifier: License :: OSI Approved :: MIT License
Classifier: Operating System :: OS Independent
Classifier: Development Status :: 4 - Beta
Classifier: Intended Audience :: Science/Research
Classifier: Topic :: Multimedia
Classifier: Topic :: Multimedia :: Sound/Audio
Classifier: Topic :: Scientific/Engineering :: Human Machine Interfaces
Classifier: Topic :: Scientific/Engineering :: Interface Engine/Protocol Translator
Requires-Dist: mido>=1.3.3
Requires-Dist: numpy>=2.2.6
Requires-Dist: pyopenxr>=1.1.5001
Requires-Dist: python-rtmidi>=1.5.8
Requires-Python: >=3.10
Project-URL: Changelog, https://git.iem.at/holzmueller/pyheadtracker/-/blob/main/CHANGELOG.md
Project-URL: Documentation, https://pyheadtracker.readthedocs.io/en/latest/
Project-URL: Homepage, https://git.iem.at/holzmueller/pyheadtracker
Project-URL: Issues, https://git.iem.at/holzmueller/pyheadtracker/-/issues
Project-URL: Repository, https://git.iem.at/holzmueller/pyheadtracker.git
